gicisky/__init__.py
gicisky/ble/__init__.py
gicisky/ble/bleak.py
gicisky/ble/interface.py
gicisky/core/__init__.py
gicisky/core/advertisement.py
gicisky/core/protocol.py
gicisky/image/__init__.py
gicisky/image/conversion.py
gicisky/image/optimizer.py
gicisky/logger/__init__.py
gicisky/logger/logger.py
gicisky-0.2.1.dist-info/licenses/LICENSE
gicisky-0.2.1.dist-info/METADATA
gicisky-0.2.1.dist-info/WHEEL
gicisky-0.2.1.dist-info/top_level.txt
gicisky-0.2.1.dist-info/RECORD
