Metadata-Version: 2.4
Name: gicisky
Version: 0.2.1
Summary: A Python library for interacting with Gicisky E-Ink display tags via Bluetooth Low Energy
Home-page: https://git.boxo.cc/massivebox/gicisky
Author: MassiveBox
Author-email: box@boxo.cc
Classifier: Development Status :: 3 - Alpha
Classifier: Intended Audience :: Developers
Classifier: License :: OSI Approved :: MIT License
Classifier: Operating System :: OS Independent
Classifier: Programming Language :: Python :: 3
Classifier: Programming Language :: Python :: 3.7
Classifier: Programming Language :: Python :: 3.8
Classifier: Programming Language :: Python :: 3.9
Classifier: Programming Language :: Python :: 3.10
Classifier: Programming Language :: Python :: 3.11
Requires-Python: >=3.7
License-File: LICENSE
Requires-Dist: bleak>=1.1.1
Requires-Dist: numpy>=2.2.6
Requires-Dist: Pillow>=12.0.0
Dynamic: author
Dynamic: author-email
Dynamic: classifier
Dynamic: description
Dynamic: description-content-type
Dynamic: home-page
Dynamic: license-file
Dynamic: requires-dist
Dynamic: requires-python
Dynamic: summary
